fanok/__init__.py
fanok/scores.py
fanok/selection.py
fanok/factor_model/__init__.py
fanok/factor_model/_shrinkage.cpython-37m-darwin.so
fanok/factor_model/factor_model.py
fanok/generation/__init__.py
fanok/generation/base.py
fanok/generation/fixed.py
fanok/generation/gaussian.py
fanok/sdp/__init__.py
fanok/sdp/_full_rank.cpython-37m-darwin.so
fanok/sdp/_full_rank_outer.cpython-37m-darwin.so
fanok/sdp/_low_rank.cpython-37m-darwin.so
fanok/sdp/sdp.py
fanok/statistics/__init__.py
fanok/statistics/base.py
fanok/statistics/centroids.py
fanok/statistics/lars.py
fanok/statistics/naive_bayes.py
fanok/utils/__init__.py
fanok/utils/_cholesky.cpython-37m-darwin.so
fanok/utils/_dtypes.cpython-37m-darwin.so
fanok/utils/_qr.cpython-37m-darwin.so
fanok/utils/base.py
fanok/utils/cholesky.py
fanok-0.0.3.dist-info/LICENSE
fanok-0.0.3.dist-info/METADATA
fanok-0.0.3.dist-info/WHEEL
fanok-0.0.3.dist-info/top_level.txt
fanok-0.0.3.dist-info/RECORD
