Metadata-Version: 2.1
Name: fanok
Version: 0.0.3
Summary: Knockoffs in Python
Home-page: https://github.com/qrebjock/fanok
Author: Armin Askari, Quentin Rebjock, Laurent El Ghaoui, and Alexandre d’Aspremont
Author-email: aaskari@berkeley.edu, quentin.rebjock@gmail.com, elghaoui@berkeley.edu, aspremon@ens.fr
License: MIT
Keywords: knockoffs,fdr,statistics
Platform: UNKNOWN
Classifier: Development Status :: 3 - Alpha
Classifier: Programming Language :: Python :: 3
Classifier: License :: OSI Approved :: MIT License
Classifier: Operating System :: OS Independent
Requires-Python: >=3.5.0
